odoo/addons/account_invoice_payment_retention/README.rst
odoo/addons/account_invoice_payment_retention/__init__.py
odoo/addons/account_invoice_payment_retention/__manifest__.py
odoo/addons/account_invoice_payment_retention/i18n/account_invoice_payment_retention.pot
odoo/addons/account_invoice_payment_retention/i18n/ca.po
odoo/addons/account_invoice_payment_retention/models/__init__.py
odoo/addons/account_invoice_payment_retention/models/account_move.py
odoo/addons/account_invoice_payment_retention/models/res_company.py
odoo/addons/account_invoice_payment_retention/models/res_config_settings.py
odoo/addons/account_invoice_payment_retention/readme/CONFIGURE.rst
odoo/addons/account_invoice_payment_retention/readme/CONTRIBUTORS.rst
odoo/addons/account_invoice_payment_retention/readme/DESCRIPTION.rst
odoo/addons/account_invoice_payment_retention/readme/USAGE.rst
odoo/addons/account_invoice_payment_retention/security/security.xml
odoo/addons/account_invoice_payment_retention/static/description/icon.png
odoo/addons/account_invoice_payment_retention/static/description/index.html
odoo/addons/account_invoice_payment_retention/tests/__init__.py
odoo/addons/account_invoice_payment_retention/tests/test_invoice_payment_retention.py
odoo/addons/account_invoice_payment_retention/views/account_move_views.xml
odoo/addons/account_invoice_payment_retention/views/res_config_settings_views.xml
odoo/addons/account_invoice_payment_retention/wizard/__init__.py
odoo/addons/account_invoice_payment_retention/wizard/account_payment_register.py
odoo/addons/account_invoice_payment_retention/wizard/account_payment_register_views.xml
odoo14_addon_account_invoice_payment_retention-14.0.1.2.0.dist-info/METADATA
odoo14_addon_account_invoice_payment_retention-14.0.1.2.0.dist-info/WHEEL
odoo14_addon_account_invoice_payment_retention-14.0.1.2.0.dist-info/top_level.txt
odoo14_addon_account_invoice_payment_retention-14.0.1.2.0.dist-info/RECORD
